LICENSE
MANIFEST.in
README.md
setup.cfg
setup.py
requirements/requirements.txt
src/os_docid/VERSION
src/os_docid/__init__.py
src/os_docid/cmdline.py
src/os_docid/x.py
src/os_docid.egg-info/PKG-INFO
src/os_docid.egg-info/SOURCES.txt
src/os_docid.egg-info/dependency_links.txt
src/os_docid.egg-info/entry_points.txt
src/os_docid.egg-info/not-zip-safe
src/os_docid.egg-info/top_level.txt
tests/test_cmdline.py
tests/test_docid.py